<?xml version="1.0" encoding="UTF-8"?>
<con:testSuite name="hw3_basic" xmlns:con="http://eviware.com/soapui/config"><con:description>TestSuite generated for REST Service [https://aberhane13-test.apigee.net]</con:description><con:settings/><con:runType>SEQUENTIAL</con:runType><con:testCase failOnError="true" failTestCaseOnErrors="true" keepSession="false" maxResults="0" name="Basic TestCase" searchProperties="true"><con:description>TestCase generated for REST Resource [Basic] located at [/hw3/basic]</con:description><con:settings/><con:testStep type="restrequest" name="basic - success"><con:settings/><con:config service="https://aberhane13-test.apigee.net" methodName="Basic" resourcePath="/hw3/basic" xsi:type="con:RestRequestStep" xmlns:xsi="http://www.w3.org/2001/XMLSchema-instance"><con:restRequest name="basic - success" mediaType="application/json"><con:settings><con:setting id="com.eviware.soapui.impl.wsdl.WsdlRequest@request-headers">&lt;entry key="Authorization" value="Basic ZHVtbXk6MTIz" xmlns="http://eviware.com/soapui/config"/></con:setting></con:settings><con:encoding>UTF-8</con:encoding><con:endpoint>https://aberhane13-test.apigee.net</con:endpoint><con:request/><con:originalUri>https://aberhane13-test.apigee.net/hw3/basic</con:originalUri><con:credentials><con:authType>No Authorization</con:authType></con:credentials><con:jmsConfig JMSDeliveryMode="PERSISTENT"/><con:jmsPropertyConfig/><con:parameters/></con:restRequest></con:config></con:testStep><con:testStep type="restrequest" name="basic - fail"><con:settings/><con:config service="https://aberhane13-test.apigee.net" methodName="Basic" resourcePath="/hw3/basic" xsi:type="con:RestRequestStep" xmlns:xsi="http://www.w3.org/2001/XMLSchema-instance"><con:restRequest name="basic - fail" mediaType="application/json"><con:settings><con:setting id="com.eviware.soapui.impl.wsdl.WsdlRequest@request-headers">&lt;entry key="Authorization" value="Basic no_token" xmlns="http://eviware.com/soapui/config"/></con:setting></con:settings><con:encoding>UTF-8</con:encoding><con:endpoint>https://aberhane13-test.apigee.net</con:endpoint><con:request/><con:originalUri>https://aberhane13-test.apigee.net/hw3/basic</con:originalUri><con:credentials><con:authType>No Authorization</con:authType></con:credentials><con:jmsConfig JMSDeliveryMode="PERSISTENT"/><con:jmsPropertyConfig/><con:parameters/></con:restRequest></con:config></con:testStep><con:properties/></con:testCase><con:properties/></con:testSuite>